<?xml version="1.0" encoding="UTF-8" ?>
<!DOCTYPE mapper
        PUBLIC "-//mybatis.org//DTD Mapper 3.0//EN"
        "http://mybatis.org/dtd/mybatis-3-mapper.dtd">
<mapper namespace="bo.ucb.edu.ingsoft.dao.PublisherDao">
    <select id="findByPublisherId" resultType="bo.ucb.edu.ingsoft.models.Publisher">
        SELECT
                id_user as idUser,
                id_publisher as idPublisher,
                paypal_mail as paypalMail,
                publisher as publisher
        FROM publishers
        WHERE
            id_user=#{idUser}
        AND
             status =1
    </select>

    <select id="findByPublisherId1" resultType="bo.ucb.edu.ingsoft.models.Publisher">
        SELECT
                id_user as idUser,
                id_publisher as idPublisher,
                paypal_mail as paypalMail,
                publisher as publisher
        FROM publishers
        WHERE
            id_publisher=#{idPublisher}
        AND
             status =1
    </select>

    <insert id="createPublisher" parameterType="bo.ucb.edu.ingsoft.models.Publisher">
        INSERT INTO publishers (id_publisher,id_user,publisher,paypal_mail,status,tx_id,tx_host,tx_user_id,tx_date)
        VALUES (
            null,
            #{idUser},
            #{publisher},
            #{paypalMail},
            1,
            #{txId},
            #{txHost},
            #{txUserId},
            #{txDate}
        )
    </insert>
    <update id="updatePublisher" parameterType="bo.ucb.edu.ingsoft.models.Publisher">
        UPDATE publishers
        SET publisher=#{publisher},
            paypal_mail=#{paypalMail},
            tx_id=#{txId},
            tx_host=#{txHost},
            tx_user_id=#{txUserId},
            tx_date=#{txDate}
        WHERE
            id_user=#{idUser}
    </update>
    <select id="listPublisher" resultType="bo.ucb.edu.ingsoft.models.Publisher">
        SELECT
                id_user as idUser,
                id_publisher as idPublisher,
                paypal_mail as paypalMail,
                publisher as publisher
        FROM publishers
        <where>
        id_user in
            <foreach collection="c" item="item" index="index"
                     open="(" separator="," close = ")">
                #{item}
            </foreach>
            and
            status = 1
            <if test="b != null">
                AND LOWER(publisher) LIKE #{b}
            </if>

            <if test="a != null and d != null">
                LIMIT #{a} OFFSET #{d}
            </if>
        </where>

    </select>

    <update id="deletePublisher" >
        UPDATE publishers
        SET  status=0
        WHERE
            id_user=#{idUser}
    </update>

    <select id="findUserIdByIdPublisher" resultType="java.lang.Integer">
        SELECT
                id_user as idUser
        FROM publishers
        WHERE
            id_publisher=#{idPublisher}

    </select>
</mapper>
